[
  {
    "id": "005b4619-6df8-4709-b6bc-88107628da12",
    "title": "Acheteuse",
    "company": "jalila lag",
    "city": "Casablanca",
    "sector": "Administratif",
    "contractType": "CDI",
    "description": "Bonjour Madame, Monsieur,\n\nC'est avec un vif intérêt que je vous adresse ma candidature au poste d'Acheteuse au sein de votre entreprise.\n\nForte d'une solide expérience dans les achats, l'approvisionnement et la gestion de la chaîne logistique, j'ai développé des compétences en sourcing fournisseurs, négociation commerciale, gestion des appels d'offres, suivi des contrats et optimisation des coûts. Mon objectif est d'assurer la disponibilité des produits et services dans les meilleures conditions de qualité, de coût et de délai.\n\nAu cours de mon parcours professionnel, j'ai été amenée à analyser les besoins des différents services, identifier et sélectionner les fournisseurs, négocier les conditions tarifaires et contractuelles, suivre les commandes jusqu'à leur livraison et évaluer la performance des partenaires. Cette expérience m'a permis de développer un excellent sens de l'organisation, de la rigueur ainsi qu'une forte capacité d'analyse et de négociation.\n\nAutonome, réactive et orientée résultats, je maîtrise les outils de gestion des achats ainsi que les principaux ERP. J'apprécie le travail en équipe et la collaboration avec les différents départements afin de garantir la fluidité des approvisionnements et de contribuer à la performance globale de l'entreprise.\n\nIntégrer votre entreprise représente pour moi une réelle opportunité de mettre mes compétences au service de vos projets et de participer activement à l'optimisation de votre politique achats.\n\nJe serais honorée de pouvoir vous rencontrer afin d'échanger sur mes motivations et les compétences que je pourrais apporter à votre équipe.\n\nDans l'attente de votre retour, je vous prie d'agréer, Madame, Monsieur, l'expression de mes salutations distinguées.",
    "requirements": "Mastère Spécialisé en Management Stratégique des Achats & Sourcing",
    "salary": null,
    "featured": false,
    "paymentId": null,
    "applicantEmail": "jalilaverdurenet@outlookfr",
    "submittedAt": "2026-07-19T18:26:00.822Z",
    "status": "pending"
  }
]